senapy/__init__.py
senapy/__version.py
senapy/model.py
senapy/service.py
senapy/dosleg/__init__.py
senapy/dosleg/opendata.py
senapy/dosleg/parser.py
senapy/parsing/__init__.py
senapy/parsing/question_search_result_parser.py
senapy-0.3.2.data/scripts/senapy-cli
tests/__init__.py
tests/test_dosleg_regressions.py
tests/test_dosleg_smoketest.py
tests/test_dosleg_unit_tests.py
tests/test_question_search_result_parsing.py
tests/test_question_search_service.py
tests/tools/__init__.py
tests/tools/_compare_outputs.py
tests/tools/add_regression_case.py
tests/tools/compare_thelawfactory_and_me.py
tests/tools/compare_with_anpy.py
tests/tools/compare_with_legipy.py
tests/tools/regen_regressions_output.py
senapy-0.3.2.dist-info/LICENSE
senapy-0.3.2.dist-info/METADATA
senapy-0.3.2.dist-info/WHEEL
senapy-0.3.2.dist-info/top_level.txt
senapy-0.3.2.dist-info/RECORD
