Metadata-Version: 2.1
Name: senapy
Version: 0.3.2
Summary: Python client for senat.fr website
Home-page: https://github.com/regardscitoyens/senapy
Author: Regards Citoyens
Author-email: contact@regardscitoyens.org
License: MIT
Keywords: scraping politics data
Platform: UNKNOWN
Classifier: Development Status :: 1 - Planning
Classifier: License :: OSI Approved :: MIT License
Classifier: Operating System :: OS Independent
Classifier: Programming Language :: Python :: 3
Requires-Dist: click (<6.8,>=6.7)
Requires-Dist: html5lib (<1.1,>=1.0)
Requires-Dist: dateparser (<0.8,>=0.7)
Requires-Dist: lawfactory-utils
